experiment_manager/__init__.py
experiment_manager/core/__init__.py
experiment_manager/core/experiment.py
experiment_manager/core/status.py
experiment_manager/integrations/__init__.py
experiment_manager/integrations/lark/__init__.py
experiment_manager/integrations/lark/bitable.py
experiment_manager/integrations/lark/sync_utils.py
experiment_manager/scheduler/__init__.py
experiment_manager/scheduler/scheduler.py
experiment_manager/scheduler/state_store.py
experiment_manager/ui/__init__.py
experiment_manager/ui/cli.py
experiment_manager/ui/server.py
experiment_manager/ui/service.py
experiment_manager/ui/static/app.js
experiment_manager/ui/static/index.html
experiment_manager/ui/static/styles.css
experiment_manager/utils/__init__.py
experiment_manager/utils/config.py
experiment_manager/utils/gpu.py
xpriment-0.0.2.dist-info/licenses/LICENSE
xpriment-0.0.2.dist-info/METADATA
xpriment-0.0.2.dist-info/WHEEL
xpriment-0.0.2.dist-info/entry_points.txt
xpriment-0.0.2.dist-info/top_level.txt
xpriment-0.0.2.dist-info/RECORD
