Metadata-Version: 2.4
Name: xpriment
Version: 0.0.2
Summary: 实验管理框架
Author: potatoQi
License: Apache-2.0
Project-URL: Homepage, https://github.com/potatoQi/EXP
Project-URL: Repository, https://github.com/potatoQi/EXP
Project-URL: Issues, https://github.com/potatoQi/EXP/issues
Keywords: experiment,scheduler,machine-learning,lark,monitoring
Classifier: Programming Language :: Python :: 3
Classifier: Programming Language :: Python :: 3.9
Classifier: Programming Language :: Python :: 3.10
Classifier: Programming Language :: Python :: 3.11
Classifier: Programming Language :: Python :: 3.12
Classifier: Operating System :: OS Independent
Classifier: Intended Audience :: Developers
Classifier: Topic :: Scientific/Engineering :: Artificial Intelligence
Classifier: Topic :: Software Development :: Build Tools
Requires-Python: >=3.9
License-File: LICENSE
Requires-Dist: toml>=0.10.2
Requires-Dist: psutil>=5.8.0
Requires-Dist: pandas>=1.3.0
Requires-Dist: fastapi>=0.111.0
Requires-Dist: uvicorn[standard]>=0.23.0
Requires-Dist: websockets>=12.0
Requires-Dist: lark-oapi>=1.0.30
Provides-Extra: dev
Requires-Dist: pytest>=8.0; extra == "dev"
Requires-Dist: pytest-asyncio>=0.23.0; extra == "dev"
Requires-Dist: httpx>=0.27.0; extra == "dev"
Dynamic: license-file
